elasticsearch7_mcp_server/__init__.py
elasticsearch7_mcp_server/es_client.py
elasticsearch7_mcp_server/server.py
mseep_elasticsearch7_mcp_server-1.0.4.dist-info/licenses/LICENSE
mseep_elasticsearch7_mcp_server-1.0.4.dist-info/METADATA
mseep_elasticsearch7_mcp_server-1.0.4.dist-info/WHEEL
mseep_elasticsearch7_mcp_server-1.0.4.dist-info/entry_points.txt
mseep_elasticsearch7_mcp_server-1.0.4.dist-info/top_level.txt
mseep_elasticsearch7_mcp_server-1.0.4.dist-info/RECORD
