Metadata-Version: 2.4
Name: mseep-elasticsearch7-mcp-server
Version: 1.0.4
Summary: MCP Server for interacting with Elasticsearch 7.x
Author-email: mseep <support@skydeck.ai>
License:                                  Apache License
Requires-Python: >=3.10
License-File: LICENSE
Requires-Dist: elasticsearch<8.0.0,>=7.0.0
Requires-Dist: mcp>=1.0.0
Requires-Dist: python-dotenv>=1.0.0
Requires-Dist: fastmcp>=0.4.0
Dynamic: license-file
